JLpy_utils_package/JL_file_utils.py
JLpy_utils_package/JL_img.py
JLpy_utils_package/JL_kaggle.py
JLpy_utils_package/JL_plot.py
JLpy_utils_package/JL_summary_tables.py
JLpy_utils_package/JL_video.py
JLpy_utils_package/__init__.py
JLpy_utils_package/img.py
JLpy_utils_package/summary_tables.py
JLpy_utils_package/video.py
JLpy_utils_package/JL_ML_models/__init__.py
JLpy_utils_package/JL_ML_models/JL_ML_inspection/JL_ML_compare.py
JLpy_utils_package/JL_ML_models/JL_ML_inspection/JL_ML_plot.py
JLpy_utils_package/JL_ML_models/JL_ML_inspection/__init__.py
JLpy_utils_package/JL_ML_models/JL_ML_model_selection/JL_ML_GridSearchCV.py
JLpy_utils_package/JL_ML_models/JL_ML_model_selection/JL_ML_default_models_dict.py
JLpy_utils_package/JL_ML_models/JL_ML_model_selection/JL_ML_model_dict.py
JLpy_utils_package/JL_ML_models/JL_ML_model_selection/__init__.py
JLpy_utils_package/JL_ML_models/JL_ML_model_selection/JL_ML_models_dict/JL_ML_fetch_models_dict.py
JLpy_utils_package/JL_ML_models/JL_ML_model_selection/JL_ML_models_dict/__init__.py
JLpy_utils_package/JL_ML_models/JL_ML_postprocessing/JL_ML_transform.py
JLpy_utils_package/JL_ML_models/JL_ML_postprocessing/__init__.py
JLpy_utils_package/JL_ML_models/JL_ML_preprocessing/JL_ML_FeatureEngineeringPipe.py
JLpy_utils_package/JL_ML_models/JL_ML_preprocessing/JL_ML_Impute.py
JLpy_utils_package/JL_ML_models/JL_ML_preprocessing/JL_ML_LabelEncode.py
JLpy_utils_package/JL_ML_models/JL_ML_preprocessing/JL_ML_OneHotEncode.py
JLpy_utils_package/JL_ML_models/JL_ML_preprocessing/JL_ML_Scale.py
JLpy_utils_package/JL_ML_models/JL_ML_preprocessing/__init__.py
JLpy_utils_package/JL_ML_models/JL_ML_preprocessing/JL_ML_feat_eng_pipe/JL_ML_FeatureEngineeringPipe.py
JLpy_utils_package/JL_ML_models/JL_ML_preprocessing/JL_ML_feat_eng_pipe/__init__.py
JLpy_utils_package/JL_ML_models/JL_NeuralNet/JL_ConvNet.py
JLpy_utils_package/JL_ML_models/JL_NeuralNet/JL_DenseNet.py
JLpy_utils_package/JL_ML_models/JL_NeuralNet/JL_NN_utils.py
JLpy_utils_package-2.0.5.dist-info/LICENSE
JLpy_utils_package-2.0.5.dist-info/METADATA
JLpy_utils_package-2.0.5.dist-info/WHEEL
JLpy_utils_package-2.0.5.dist-info/top_level.txt
JLpy_utils_package-2.0.5.dist-info/RECORD
