Metadata-Version: 2.1
Name: JLpy-utils-package
Version: 2.0.5
Summary: Custom methodes for various data science, computer vision, and machine learning operations in python
Home-page: https://github.com/jlnerd/JLpy_utils_package.git
Author: John T. Leonard
Author-email: jtleona01@gmail.com
License: UNKNOWN
Platform: UNKNOWN
Requires-Dist: numpy (>=1.14.6)
Requires-Dist: pandas (>=0.25.1)
Requires-Dist: sklearn
Requires-Dist: scipy
Requires-Dist: matplotlib
